FlexiKit/DLL.py
FlexiKit/Memory.py
FlexiKit/Memorydll.dll
FlexiKit/UI.py
FlexiKit/__init__.py
FlexiKit/math.py
FlexiKit/time.py
flexikit-0.1.2.dist-info/METADATA
flexikit-0.1.2.dist-info/WHEEL
flexikit-0.1.2.dist-info/top_level.txt
flexikit-0.1.2.dist-info/RECORD
